Metadata-Version: 2.2
Name: axonml
Version: 0.1.1
Summary: A lightweight machine learning library implementing fundamental ML algorithms
Author: Akshaya Ramesh Nagarajan
Author-email: akshayaramesh03@gmail.com
Classifier: Programming Language :: Python :: 3
Classifier: License :: OSI Approved :: MIT License
Classifier: Operating System :: OS Independent
Requires-Python: >=3.8
License-File: LICENSE
Requires-Dist: numpy>=1.19.0
Dynamic: author
Dynamic: author-email
Dynamic: classifier
Dynamic: description
Dynamic: description-content-type
Dynamic: requires-dist
Dynamic: requires-python
Dynamic: summary
